{
  "二游": [
    {
      "time": "2026-02-18 19:08:19",
      "value": 2046.51
    },
    {
      "time": "2026-02-18 19:08:20",
      "value": 2538.92
    },
    {
      "time": "2026-02-18 19:08:21",
      "value": 3035.16
    },
    {
      "time": "2026-02-18 19:08:22",
      "value": 4216.58
    },
    {
      "time": "2026-02-18 19:08:24",
      "value": 4993.73
    },
    {
      "time": "2026-02-18 19:10:00",
      "value": 4993.73
    },
    {
      "time": "2026-02-18 19:10:01",
      "value": 4993.73
    },
    {
      "time": "2026-02-18 19:10:03",
      "value": 4993.73
    },
    {
      "time": "2026-02-18 19:10:04",
      "value": 4993.73
    },
    {
      "time": "2026-02-18 19:10:05",
      "value": 4993.73
    },
    {
      "time": "2026-02-18 19:15:57",
      "value": 4993.73
    },
    {
      "time": "2026-02-18 19:15:58",
      "value": 4993.73
    },
    {
      "time": "2026-02-18 19:15:59",
      "value": 4993.73
    },
    {
      "time": "2026-02-18 19:16:01",
      "value": 4993.73
    },
    {
      "time": "2026-02-18 19:16:02",
      "value": 4993.73
    },
    {
      "time": "2026-02-18 19:18:16",
      "value": 4993.73
    },
    {
      "time": "2026-02-18 19:18:17",
      "value": 4993.73
    },
    {
      "time": "2026-02-18 19:18:18",
      "value": 4993.73
    },
    {
      "time": "2026-02-18 19:18:19",
      "value": 4993.73
    },
    {
      "time": "2026-02-18 19:18:20",
      "value": 4993.73
    },
    {
      "time": "2026-02-18 19:24:48",
      "value": 4993.73
    },
    {
      "time": "2026-02-18 19:24:49",
      "value": 4993.73
    },
    {
      "time": "2026-02-18 19:24:50",
      "value": 4993.73
    },
    {
      "time": "2026-02-18 19:24:51",
      "value": 4993.73
    },
    {
      "time": "2026-02-18 19:24:53",
      "value": 4993.73
    },
    {
      "time": "2026-02-18 19:51:33",
      "value": 4993.73
    },
    {
      "time": "2026-02-18 19:51:35",
      "value": 4993.73
    },
    {
      "time": "2026-02-18 19:51:36",
      "value": 4993.73
    },
    {
      "time": "2026-02-18 19:51:38",
      "value": 4993.74
    },
    {
      "time": "2026-02-18 19:51:39",
      "value": 4993.74
    },
    {
      "time": "2026-02-19 01:07:36",
      "value": 4993.74
    },
    {
      "time": "2026-02-19 01:07:37",
      "value": 4993.74
    },
    {
      "time": "2026-02-19 01:07:39",
      "value": 4993.76
    },
    {
      "time": "2026-02-19 01:07:40",
      "value": 4993.8
    },
    {
      "time": "2026-02-19 01:07:42",
      "value": 4993.81
    },
    {
      "time": "2026-02-19 06:45:21",
      "value": 4993.82
    },
    {
      "time": "2026-02-19 06:45:22",
      "value": 4993.82
    },
    {
      "time": "2026-02-19 06:45:23",
      "value": 4993.87
    },
    {
      "time": "2026-02-19 06:45:25",
      "value": 4994.05
    },
    {
      "time": "2026-02-19 06:45:26",
      "value": 4994.07
    }
  ],
  "蓝筹100": [
    {
      "time": "2026-02-18 19:08:19",
      "value": 0.0
    },
    {
      "time": "2026-02-18 19:08:20",
      "value": 0.0
    },
    {
      "time": "2026-02-18 19:08:21",
      "value": 0.0
    },
    {
      "time": "2026-02-18 19:08:22",
      "value": 0.0
    },
    {
      "time": "2026-02-18 19:08:24",
      "value": 777.15
    },
    {
      "time": "2026-02-18 19:10:00",
      "value": 777.15
    },
    {
      "time": "2026-02-18 19:10:01",
      "value": 777.15
    },
    {
      "time": "2026-02-18 19:10:03",
      "value": 777.15
    },
    {
      "time": "2026-02-18 19:10:04",
      "value": 777.15
    },
    {
      "time": "2026-02-18 19:10:05",
      "value": 777.15
    },
    {
      "time": "2026-02-18 19:15:57",
      "value": 777.15
    },
    {
      "time": "2026-02-18 19:15:58",
      "value": 777.15
    },
    {
      "time": "2026-02-18 19:15:59",
      "value": 777.15
    },
    {
      "time": "2026-02-18 19:16:01",
      "value": 777.15
    },
    {
      "time": "2026-02-18 19:16:02",
      "value": 777.15
    },
    {
      "time": "2026-02-18 19:18:16",
      "value": 777.15
    },
    {
      "time": "2026-02-18 19:18:17",
      "value": 777.15
    },
    {
      "time": "2026-02-18 19:18:18",
      "value": 777.15
    },
    {
      "time": "2026-02-18 19:18:19",
      "value": 777.15
    },
    {
      "time": "2026-02-18 19:18:20",
      "value": 777.15
    },
    {
      "time": "2026-02-18 19:24:48",
      "value": 777.15
    },
    {
      "time": "2026-02-18 19:24:49",
      "value": 777.15
    },
    {
      "time": "2026-02-18 19:24:50",
      "value": 777.15
    },
    {
      "time": "2026-02-18 19:24:51",
      "value": 777.15
    },
    {
      "time": "2026-02-18 19:24:53",
      "value": 777.15
    },
    {
      "time": "2026-02-18 19:51:33",
      "value": 777.15
    },
    {
      "time": "2026-02-18 19:51:35",
      "value": 777.15
    },
    {
      "time": "2026-02-18 19:51:36",
      "value": 777.15
    },
    {
      "time": "2026-02-18 19:51:38",
      "value": 777.15
    },
    {
      "time": "2026-02-18 19:51:39",
      "value": 777.15
    },
    {
      "time": "2026-02-19 01:07:36",
      "value": 777.15
    },
    {
      "time": "2026-02-19 01:07:37",
      "value": 777.15
    },
    {
      "time": "2026-02-19 01:07:39",
      "value": 777.15
    },
    {
      "time": "2026-02-19 01:07:40",
      "value": 777.15
    },
    {
      "time": "2026-02-19 01:07:42",
      "value": 777.16
    },
    {
      "time": "2026-02-19 06:45:21",
      "value": 777.16
    },
    {
      "time": "2026-02-19 06:45:22",
      "value": 777.16
    },
    {
      "time": "2026-02-19 06:45:23",
      "value": 777.16
    },
    {
      "time": "2026-02-19 06:45:25",
      "value": 777.16
    },
    {
      "time": "2026-02-19 06:45:26",
      "value": 777.18
    }
  ]
}